LICENSE
README.md
setup.py
terraform_vsphere_provider_wrapper.py
lib/terraform-provider-vsphere_v2.0.2_x5
terraform_vsphere_provider_wrapper.egg-info/PKG-INFO
terraform_vsphere_provider_wrapper.egg-info/SOURCES.txt
terraform_vsphere_provider_wrapper.egg-info/dependency_links.txt
terraform_vsphere_provider_wrapper.egg-info/entry_points.txt
terraform_vsphere_provider_wrapper.egg-info/top_level.txt