Metadata-Version: 2.1
Name: terraform-vsphere-provider-wrapper
Version: 2.0.2.post4
Summary: Python wrapper for Terraform Vsphere Provider
Home-page: https://github.com/imanazari70/terraform-vsphere-provider-wrapper
Author: Iman Azari
Author-email: azari@mahsan.co
License-File: LICENSE
